lib/CodeRunner.py
lib/MultifileCodeRunner.py
lib/OneFileCodeRunner.py
lib/__init__.py
lib/api_utils.py
lib/custom_parser.py
lib/executeCode.py
lib/utils.py
nowledgeable/CommandTester.py
nowledgeable/InMemoryPythonRunner.py
nowledgeable/JsonEncoder.py
nowledgeable/PythonRunner.py
nowledgeable/__init__.py
nowledgeable/command_utils.py
nowledgeable/external_exercice_tools.py
nowledgeable/main.py
nowledgeable/math_utils.py
nowledgeable/notebook_test.py
nowledgeable/notebook_utils.py
nowledgeable/trace.py
nowledgeable/utils.py
nowledgeable-0.1.12.dist-info/LICENSE
nowledgeable-0.1.12.dist-info/METADATA
nowledgeable-0.1.12.dist-info/WHEEL
nowledgeable-0.1.12.dist-info/entry_points.txt
nowledgeable-0.1.12.dist-info/top_level.txt
nowledgeable-0.1.12.dist-info/RECORD
