Metadata-Version: 2.1
Name: nowledgeable
Version: 0.1.12
Summary: Auto checker
Home-page: https://www.python.org/sigs/distutils-sig/
Author: Laurent CETINSOY
Author-email: laurent.cetinsoy+pypi@nowledgeable.com
License: UNKNOWN
Project-URL: Bug Tracker, https://gitlab.com/nowledgeable/nowledgeable/-/incidents
Platform: UNKNOWN
Classifier: License :: OSI Approved :: GNU Affero General Public License v3
Requires-Python: >=3.6
License-File: LICENSE
Requires-Dist: pandas
Requires-Dist: pyyaml
Requires-Dist: matplotlib
Requires-Dist: werkzeug
Requires-Dist: numpy
Requires-Dist: requests
Requires-Dist: scipy
Requires-Dist: watchdog
